esbmc_wr/__init__.py
esbmc_wr/bar/__init__.py
esbmc_wr/bar/bar.py
esbmc_wr/bin/esbmc
esbmc_wr/csvwr/__init__.py
esbmc_wr/csvwr/csvwr.py
esbmc_wr/log/__init__.py
esbmc_wr/log/log.py
esbmc_wr/utils/__init__.py
esbmc_wr/utils/shell.py
esbmc_wr/utils/utils.py
esbmc_wr-0.2.0.dist-info/LICENSE
esbmc_wr-0.2.0.dist-info/METADATA
esbmc_wr-0.2.0.dist-info/WHEEL
esbmc_wr-0.2.0.dist-info/entry_points.txt
esbmc_wr-0.2.0.dist-info/top_level.txt
esbmc_wr-0.2.0.dist-info/RECORD
