Metadata-Version: 2.1
Name: esbmc-wr
Version: 0.2.0
Summary: A ESBMC command line wrapper.
Home-page: https://github.com/thalestas/esbmc-wr
Author: Thales Silva
Author-email: thales.tas@gmail.com
License: MIT
Platform: UNKNOWN
Classifier: License :: OSI Approved :: MIT License
Classifier: Programming Language :: Python
Classifier: Programming Language :: Python :: 3
Classifier: Programming Language :: Python :: 3.6
Classifier: Programming Language :: Python :: Implementation :: CPython
Classifier: Programming Language :: Python :: Implementation :: PyPy
Requires-Python: >=3.6.0
Requires-Dist: tqdm
